{
    "nigga": [
        {
            "1968": 0.0
        },
        {
            "1970": 0.0
        },
        {
            "1971": 0.0
        },
        {
            "1972": 0.0
        },
        {
            "1973": 0.0
        },
        {
            "1974": 2.4390243902439024
        },
        {
            "1975": 0.0
        },
        {
            "1976": 0.0
        },
        {
            "1977": 0.0
        },
        {
            "1978": 4.914004914004914
        },
        {
            "1979": 0.0
        },
        {
            "1980": 0.0
        },
        {
            "1981": 0.0
        },
        {
            "1982": 0.0
        },
        {
            "1983": 0.0
        },
        {
            "1984": 0.0
        },
        {
            "1985": 0.0
        },
        {
            "1986": 0.0
        },
        {
            "1987": 0.0
        },
        {
            "1988": 0.0
        },
        {
            "1989": 0.0
        },
        {
            "1990": 0.0
        },
        {
            "1991": 30.41144901610018
        },
        {
            "1992": 14.332965821389195
        },
        {
            "1993": 0.0
        },
        {
            "1994": 71.28099173553719
        },
        {
            "1995": 165.51724137931035
        },
        {
            "1996": 84.14239482200647
        },
        {
            "1997": 3.834355828220859
        },
        {
            "1998": 105.05836575875486
        },
        {
            "1999": 120.42875157629256
        },
        {
            "2000": 169.57026713124273
        },
        {
            "2001": 63.69426751592356
        },
        {
            "2002": 190.91751621872103
        },
        {
            "2003": 101.05166895290353
        },
        {
            "2004": 241.75229853975122
        },
        {
            "2005": 162.6158419304074
        },
        {
            "2006": 172.30708969839404
        },
        {
            "2007": 109.9140977118897
        },
        {
            "2008": 107.13122761315532
        },
        {
            "2009": 107.32396707955773
        },
        {
            "2010": 142.40872294729886
        },
        {
            "2011": 155.96254247120245
        },
        {
            "2012": 182.40547216416493
        },
        {
            "2013": 138.7686803992845
        },
        {
            "2014": 126.33628318584071
        },
        {
            "2015": 108.11374539386776
        },
        {
            "2016": 90.27239434360715
        }
    ]
}